nndeploy/__init__.py
nndeploy/_nndeploy_internal.cpython-310-x86_64-linux-gnu.so
nndeploy/_nndeploy_internal.cpython-311-x86_64-linux-gnu.so
nndeploy/libMNN.so
nndeploy/libMNN_Express.so
nndeploy/libllm.so
nndeploy/libnndeploy_framework.so
nndeploy/libnndeploy_plugin_basic.so
nndeploy/libnndeploy_plugin_classification.so
nndeploy/libnndeploy_plugin_codec.so
nndeploy/libnndeploy_plugin_detect.so
nndeploy/libnndeploy_plugin_infer.so
nndeploy/libnndeploy_plugin_llm.so
nndeploy/libnndeploy_plugin_matting.so
nndeploy/libnndeploy_plugin_ocr.so
nndeploy/libnndeploy_plugin_preprocess.so
nndeploy/libnndeploy_plugin_qwen.so
nndeploy/libnndeploy_plugin_segment.so
nndeploy/libnndeploy_plugin_stable_diffusion.so
nndeploy/libnndeploy_plugin_super_resolution.so
nndeploy/libnndeploy_plugin_tokenizer.so
nndeploy/libnndeploy_plugin_track.so
nndeploy/libonnxruntime.so.1.18.0
nndeploy/libopencv_calib3d.so.4.10.0
nndeploy/libopencv_calib3d.so.410
nndeploy/libopencv_core.so.4.10.0
nndeploy/libopencv_core.so.410
nndeploy/libopencv_dnn.so.4.10.0
nndeploy/libopencv_dnn.so.410
nndeploy/libopencv_features2d.so.4.10.0
nndeploy/libopencv_features2d.so.410
nndeploy/libopencv_flann.so.4.10.0
nndeploy/libopencv_flann.so.410
nndeploy/libopencv_highgui.so.4.10.0
nndeploy/libopencv_highgui.so.410
nndeploy/libopencv_imgcodecs.so.4.10.0
nndeploy/libopencv_imgcodecs.so.410
nndeploy/libopencv_imgproc.so.4.10.0
nndeploy/libopencv_imgproc.so.410
nndeploy/libopencv_video.so.4.10.0
nndeploy/libopencv_video.so.410
nndeploy/libopencv_videoio.so.4.10.0
nndeploy/libopencv_videoio.so.410
nndeploy/nndeploy.py
nndeploy/api_aigc/__init__.py
nndeploy/api_aigc/openai_plugin.py
nndeploy/api_llm/__init__.py
nndeploy/api_llm/llm_chat.py
nndeploy/base/__init__.py
nndeploy/base/common.py
nndeploy/base/logger.py
nndeploy/base/similarity.py
nndeploy/base/torch_util.py
nndeploy/basic/__init__.py
nndeploy/basic/input.py
nndeploy/basic/pil_numpy_pt.py
nndeploy-3.0.8.dist-info/METADATA
nndeploy-3.0.8.dist-info/WHEEL
nndeploy-3.0.8.dist-info/entry_points.txt
nndeploy-3.0.8.dist-info/top_level.txt
nndeploy-3.0.8.dist-info/RECORD
