Metadata-Version: 2.1
Name: nndeploy
Version: 3.0.8
Summary: An Easy-to-Use and High-Performance AI deployment framework
Home-page: https://github.com/nndeploy/nndeploy
Author: nndeploy team
Author-email: 595961667@qq.com
License: Apache License 2.0
Project-URL: Bug Reports, https://github.com/nndeploy/nndeploy/issues
Project-URL: Source, https://github.com/nndeploy/nndeploy
Keywords: deep-learning,visual-workflow,ai-agent,easy-to-use,high-performance
Classifier: Development Status :: 4 - Beta
Classifier: Intended Audience :: Developers
Classifier: License :: OSI Approved :: Apache Software License
Classifier: Operating System :: OS Independent
Classifier: Programming Language :: C++
Classifier: Programming Language :: Python :: 3.10
Classifier: Programming Language :: Python :: 3.11
Classifier: Programming Language :: Python :: 3.12
Classifier: Programming Language :: Python :: 3.13
Classifier: Programming Language :: Python :: 3.14
Classifier: Topic :: Scientific/Engineering :: Artificial Intelligence
Requires-Python: >=3.10
Requires-Dist: cython
Requires-Dist: packaging
Requires-Dist: Pillow
Requires-Dist: numpy
Requires-Dist: opencv-python>=4.10.0
Requires-Dist: modelscope
Requires-Dist: multiprocess
Requires-Dist: requests>=2.31.0
Requires-Dist: fastapi>=0.104.0
Requires-Dist: uvicorn>=0.24.0
Requires-Dist: websockets>=11.0
Requires-Dist: python-multipart>=0.0.6
Requires-Dist: pydantic>=2.0.0
Requires-Dist: chardet>=5.2.0
